comtacts/__init__.py
comtacts/cli.py
comtacts/comtacts.py
comtacts-0.1.0.dist-info/METADATA
comtacts-0.1.0.dist-info/WHEEL
comtacts-0.1.0.dist-info/entry_points.txt
comtacts-0.1.0.dist-info/licenses/LICENSE
comtacts-0.1.0.dist-info/RECORD
