Metadata-Version: 2.3
Name: comtacts
Version: 0.1.0
Summary: A tool to remember and detect communication ports using hardware identifiers
Author-email: Rishi Kumar <rekumar@icloud.com>
Classifier: License :: OSI Approved :: MIT License
Classifier: Operating System :: OS Independent
Classifier: Programming Language :: Python :: 3
Requires-Python: >=3.10
Requires-Dist: click>=8.0
Requires-Dist: pyserial>=3.5
Provides-Extra: dev
Requires-Dist: pytest-cov>=4.0; extra == 'dev'
Requires-Dist: pytest>=7.0; extra == 'dev'
